outta/__init__.py
outta/cli.py
outta/elements.py
outta/parser.py
outta/version.py
outta-0.3.1.dist-info/LICENSE
outta-0.3.1.dist-info/METADATA
outta-0.3.1.dist-info/WHEEL
outta-0.3.1.dist-info/entry_points.txt
outta-0.3.1.dist-info/top_level.txt
outta-0.3.1.dist-info/RECORD
