Metadata-Version: 2.1
Name: outta
Version: 0.3.1
Summary: ANSI control code parsing
Home-page: http://github.com/abingham/outta
Author: Austin Bingham
Author-email: austin.bingham@protonmail.com
License: LGPL
Platform: any
Classifier: Development Status :: 3 - Alpha
Classifier: Operating System :: OS Independent
Classifier: Programming Language :: Python
Classifier: Programming Language :: Python :: 3 :: Only
Classifier: Programming Language :: Python :: 3.10
License-File: LICENSE
Requires-Dist: pyte
Provides-Extra: dev
Requires-Dist: black ; extra == 'dev'
Requires-Dist: bump2version ; extra == 'dev'
Requires-Dist: flake8 ; extra == 'dev'
Provides-Extra: test
Requires-Dist: pytest ; extra == 'test'
